IndianPinCodes/__init__.py
IndianPinCodes/pin.py
IndianPinCodes-0.0.7.dist-info/=3.6
IndianPinCodes-0.0.7.dist-info/METADATA
IndianPinCodes-0.0.7.dist-info/WHEEL
IndianPinCodes-0.0.7.dist-info/top_level.txt
IndianPinCodes-0.0.7.dist-info/RECORD
