Metadata-Version: 2.1
Name: IndianPinCodes
Version: 0.0.7
Summary: A package for fetching details for the pincode provided
Home-page: https://github.com/LpCodes/Pincode-Details
Author: Lpcodes
Project-URL: Bug Tracker, https://github.com/LpCodes/Pincode-Details/issues
Keywords: India Indian pincodes pin codes
Classifier: Programming Language :: Python :: 3
Classifier: License :: OSI Approved :: MIT License
Classifier: Operating System :: OS Independent
Requires-Python: >=3.6
Requires-Dist: requests
